centralpy/__init__.py
centralpy/__main__.py
centralpy/__version__.py
centralpy/check_audits.py
centralpy/cli.py
centralpy/client.py
centralpy/decorators.py
centralpy/errors.py
centralpy/loggers.py
centralpy/responses/__init__.py
centralpy/responses/attachment.py
centralpy/responses/attachment_listing.py
centralpy/responses/csv_zip.py
centralpy/responses/form_listing.py
centralpy/responses/project_listing.py
centralpy/responses/response.py
centralpy/responses/submission_listing.py
centralpy/use_cases/__init__.py
centralpy/use_cases/check_connection.py
centralpy/use_cases/download_attachments.py
centralpy/use_cases/pull_csv_zip.py
centralpy/use_cases/push_submissions_and_attachments.py
centralpy/use_cases/server_audits.py
centralpy/use_cases/upload_attachments.py
centralpy-0.6.1.dist-info/LICENSE
centralpy-0.6.1.dist-info/METADATA
centralpy-0.6.1.dist-info/WHEEL
centralpy-0.6.1.dist-info/entry_points.txt
centralpy-0.6.1.dist-info/top_level.txt
centralpy-0.6.1.dist-info/RECORD
