Metadata-Version: 2.1
Name: centralpy
Version: 0.6.1
Summary: A Python client for ODK Central
Home-page: https://github.com/pmaengineering/central
Author: James Pringle
Author-email: jpringle@jhu.edu
License: MIT
Platform: UNKNOWN
Classifier: License :: OSI Approved :: MIT License
Classifier: Programming Language :: Python
Classifier: Programming Language :: Python :: 3
Classifier: Programming Language :: Python :: 3.6
Classifier: Programming Language :: Python :: 3.7
Classifier: Programming Language :: Python :: 3.8
Classifier: Programming Language :: Python :: 3.9
Classifier: Programming Language :: Python :: Implementation :: CPython
Requires-Python: >=3.6.0
Requires-Dist: requests (>=2.26.0)
Requires-Dist: click (>=8.0.0)
Requires-Dist: tqdm (>=4.62.0)
Requires-Dist: werkzeug (>=2.0.2)
